LICENSE.txt
README.md
setup.py
aiotoolsbox/__init__.py
aiotoolsbox/compat.py
aiotoolsbox/context.py
aiotoolsbox/defer.py
aiotoolsbox/fork.py
aiotoolsbox/func.py
aiotoolsbox/iter.py
aiotoolsbox/server.py
aiotoolsbox/timer.py
aiotoolsbox.egg-info/PKG-INFO
aiotoolsbox.egg-info/SOURCES.txt
aiotoolsbox.egg-info/dependency_links.txt
aiotoolsbox.egg-info/requires.txt
aiotoolsbox.egg-info/top_level.txt