Metadata-Version: 2.1
Name: aiotoolsbox
Version: 1.4.7
Summary: Idiomatic asyncio utilities
Home-page: https://github.com/achimnol/aiotools
Author: Joongi Kim
Author-email: me@daybreaker.info
License: apache2
Classifier: Programming Language :: Python :: 3.8
Classifier: Programming Language :: Python :: 3.9
Classifier: Programming Language :: Python :: 3.10
Classifier: License :: OSI Approved :: Apache Software License
Requires-Python: >=3.8, <=3.10
License-File: LICENSE.txt
